unitoken/__init__.py
unitoken/client.py
unitoken/openai_adapter.py
unitoken-0.1.0.dist-info/METADATA
unitoken-0.1.0.dist-info/WHEEL
unitoken-0.1.0.dist-info/RECORD
