Metadata-Version: 2.4
Name: unitoken
Version: 0.1.0
Summary: UniToken Python SDK - Unified token management for AI applications
Project-URL: Homepage, https://uni-token.app
Project-URL: Documentation, https://docs.uni-token.app/
Project-URL: Repository, https://github.com/uni-token/core
Project-URL: Issues, https://github.com/uni-token/core/issues
Author-email: _Kerman <kermanx@qq.com>
License: MIT
Keywords: ai,api,openai,sdk,token,unitoken
Classifier: Intended Audience :: Developers
Classifier: License :: OSI Approved :: MIT License
Classifier: Programming Language :: Python :: 3
Classifier: Programming Language :: Python :: 3.8
Classifier: Programming Language :: Python :: 3.9
Classifier: Programming Language :: Python :: 3.10
Classifier: Programming Language :: Python :: 3.11
Classifier: Programming Language :: Python :: 3.12
Classifier: Topic :: Internet :: WWW/HTTP :: HTTP Servers
Classifier: Topic :: Software Development :: Libraries :: Python Modules
Requires-Python: >=3.8
Requires-Dist: requests>=2.25.0
